{
  "transactions": [
    {
      "id": 1,
      "description": "Desenvolvimento de site",
      "type": "income",
      "category": "Venda",
      "price": 39000,
      "createdAt": "2023-07-31T21:52:35.543Z"
    },
    {
      "id": 2,
      "description": "Compra de software",
      "type": "outcome",
      "category": "Compra",
      "price": 25000,
      "createdAt": "2023-07-31T21:45:35.543Z"
    },
    {
      "id": 3,
      "description": "Compra do mês da casa",
      "type": "outcome",
      "category": "Alimentação",
      "price": 540,
      "createdAt": "2023-07-31T17:45:35.543Z"
    },
    {
      "description": "Hamburguer",
      "price": 49,
      "category": "Alimentação",
      "type": "outcome",
      "createdAt": "2023-08-01T23:05:57.789Z",
      "id": 4
    },
    {
      "description": "Cereais",
      "price": 11,
      "category": "Alimentação",
      "type": "outcome",
      "createdAt": "2023-08-01T23:06:39.940Z",
      "id": 5
    }
  ]
}